minio_adapter/__init__.py
minio_adapter/async_client.py
minio_adapter/client.py
minio_adapter/config.py
minio_adapter/health.py
minio_adapter/logging_config.py
evolvishub_minio_adapter-0.1.2.dist-info/METADATA
evolvishub_minio_adapter-0.1.2.dist-info/WHEEL
evolvishub_minio_adapter-0.1.2.dist-info/top_level.txt
evolvishub_minio_adapter-0.1.2.dist-info/RECORD
